jmusched/__init__.py
jmusched/__version__.py
jmusched/classes.py
jmusched/main.py
jmusched-0.1.0.dist-info/LICENSE.md
jmusched-0.1.0.dist-info/METADATA
jmusched-0.1.0.dist-info/WHEEL
jmusched-0.1.0.dist-info/entry_points.txt
jmusched-0.1.0.dist-info/top_level.txt
jmusched-0.1.0.dist-info/RECORD
